gev/__init__.py
gev/test_gev.py
gev/utils.py
gev-0.1.2.dist-info/LICENSE
gev-0.1.2.dist-info/WHEEL
gev-0.1.2.dist-info/METADATA
gev-0.1.2.dist-info/RECORD
