Metadata-Version: 2.1
Name: gev
Version: 0.1.2
Summary: General Events Manager
Home-page: https://github.com/wonderbeyond/gev
License: MIT
Keywords: python,events
Author: Wonder
Author-email: wonderbeyond@gmail.com
Requires-Python: >=3.8,<4.0
Classifier: Intended Audience :: Developers
Classifier: License :: OSI Approved :: MIT License
Classifier: Operating System :: OS Independent
Classifier: Programming Language :: Python :: 3
Classifier: Programming Language :: Python :: 3.8
Classifier: Programming Language :: Python :: 3.9
Classifier: Programming Language :: Python :: 3.10
Classifier: Programming Language :: Python :: 3.11
Classifier: Programming Language :: Python :: 3
Classifier: Topic :: Software Development :: Libraries :: Python Modules
Provides-Extra: testing
Requires-Dist: pytest (>=7.1.2,<8.0.0); extra == "testing"
Requires-Dist: pytest-asyncio (>=0.20.2,<0.21.0); extra == "testing"
Project-URL: Documentation, https://github.com/wonderbeyond/gev
Project-URL: Repository, https://github.com/wonderbeyond/gev
